pypeaks/__init__.py
pypeaks/data.py
pypeaks/intervals.py
pypeaks/slope.py
pypeaks/examples/howto.ipynb
pypeaks/examples/howto.py
pypeaks/examples/ji-intervals.pickle
pypeaks/examples/sample-histogram.pickle
pypeaks-2025.3.28.dist-info/licenses/LICENSE
pypeaks-2025.3.28.dist-info/METADATA
pypeaks-2025.3.28.dist-info/WHEEL
pypeaks-2025.3.28.dist-info/top_level.txt
pypeaks-2025.3.28.dist-info/RECORD
