Metadata-Version: 2.4
Name: pypeaks
Version: 2025.3.28
Summary: Python module with different methods to identify peaks from data like histograms and time-series data
Author-email: Gopala Krishna Koduri <gopala.koduri@gmail.com>
License: AGPL-3.0-only
Project-URL: Homepage, https://github.com/gopalkoduri/pypeaks
Keywords: python,peaks,histogram,time-series,maxima,minima
Classifier: Development Status :: 4 - Beta
Classifier: Programming Language :: Python :: 3.8
Classifier: Programming Language :: Python :: 3.9
Classifier: Programming Language :: Python :: 3.10
Classifier: Programming Language :: Python :: 3.11
Classifier: Topic :: Scientific/Engineering :: Information Analysis
Classifier: Topic :: Software Development :: Libraries :: Python Modules
Classifier: License :: OSI Approved :: GNU Affero General Public License v3
License-File: LICENSE
Requires-Dist: numpy
Requires-Dist: matplotlib
Dynamic: license-file
